{
  "annotations": {
    "changelogDate": "20240719231426"
  },
  "applications": ["jhipster"],
  "fields": [
    {
      "fieldName": "firstName",
      "fieldType": "String"
    },
    {
      "fieldName": "lastName",
      "fieldType": "String"
    },
    {
      "fieldName": "email",
      "fieldType": "String"
    },
    {
      "fieldName": "telephone",
      "fieldType": "String"
    }
  ],
  "name": "Customer",
  "pagination": "pagination",
  "relationships": [
    {
      "otherEntityName": "address",
      "otherEntityRelationshipName": "customer",
      "relationshipName": "address",
      "relationshipSide": "left",
      "relationshipType": "one-to-many"
    }
  ],
  "searchEngine": "no"
}
